snailshell/__init__.py
snailshell/main.py
snailshell/main_test.py
snailshell/adapters/base.py
snailshell/frame_loader/base.py
snailshell/frame_loader/opencv_backend.py
snailshell/frame_loader/opencv_backend_test.py
snailshell/frame_loader/picamera_backend.py
snailshell/model_loader/mobilenet.py
snailshell/model_loader/resnet.py
snailshell/models/mobilenet.py
snailshell/models/model-ai-sink-run/config.json
snailshell/models/model-ai-sink-run/model.safetensors
snailshell/models/model-ai-sink-run/training_args.bin
snailshell/pipelines/base.py
snailshell/tools/datalakeuploader.py
snailshell/tools/modeldownloader.py
snailshell-1.2.2.dist-info/entry_points.txt
snailshell-1.2.2.dist-info/WHEEL
snailshell-1.2.2.dist-info/METADATA
snailshell-1.2.2.dist-info/RECORD
