Metadata-Version: 2.1
Name: snailshell
Version: 1.2.2
Summary: 싱크대 자동 수전 절수 시스템
Author-email: Janghoo Lee <dlwkdgn1@naver.com>, Subin Jang <subinaksl@naver.com>, Seokwoo Ahn <patrick0503@naver.com>, Dahyun Kim <builtforlove@naver.com>
Requires-Python: >=3.8
Classifier: License :: OSI Approved :: MIT License
Requires-Dist: PyYAML
Requires-Dist: torch
Requires-Dist: numpy
Requires-Dist: torchvision
Requires-Dist: transformers
Requires-Dist: opencv-python
Requires-Dist: pyserial
Requires-Dist: pytz
Requires-Dist: wandb
Requires-Dist: autosink-data-elt
Requires-Dist: google-api-python-client
Requires-Dist: discord-webhook
Requires-Dist: flit ; extra == "dev"
Requires-Dist: pylint ; extra == "dev"
Requires-Dist: yapf ; extra == "dev"
Requires-Dist: python-dotenv ; extra == "dev"
Requires-Dist: requests ; extra == "dev"
Provides-Extra: dev
